VerTest/src/vercode/test2.v
module test2
(
    input a,
    input b,
    output c
);
    assign c = a ^ b;
endmodule

VerTest/src/test2.vcd
$version Generated by VerilatedVcd $end
$timescale 1ps $end

 $scope module TOP $end
  $var wire  1 # a $end
  $var wire  1 $ b $end
  $var wire  1 % c $end
  $scope module test2 $end
   $var wire  1 # a $end
   $var wire  1 $ b $end
   $var wire  1 % c $end
  $upscope $end
 $upscope $end
$enddefinitions $end


#1
1#
0$
1%
#2
1$
0%
#3
#4
0#
0$
#5
1#
1$
#6
0#
1%
#7
#8
1#
0$
#9
0#
0%
#10
#11
1#
1%
#12
1$
0%
#13
0#
0$
#14
1$
1%
#15
1#
0%
#16
0$
1%
#17
0#
0%
#18
1#
1$
#19
0$
1%
#20
#21
1$
0%
#22
#23
0#
1%
#24
0$
0%
#25
1#
1%
#26
#27
#28
0#
1$
#29
0$
0%
#30
1$
1%
#31
1#
0%
#32
0#
1%
#33
#34
#35
1#
0%
#36
0#
1%
#37
#38
#39
0$
0%
#40
1#
1%
#41
#42
0#
0%
#43
#44
1#
1$
#45
0#
1%
#46
0$
0%
#47
#48
1#
1%
#49
0#
0%
#50
1$
1%
#51
1#
0$
#52
0#
0%
#53
1#
1$
#54
0$
1%
#55
#56
0#
0%
#57
1#
1%
#58
0#
1$
#59
1#
0%
#60
0#
1%
#61
#62
1#
0%
#63
#64
#65
#66
0$
1%
#67
1$
0%
#68
0#
1%
#69
#70
1#
0$
#71
0#
1$
#72
#73
1#
0%
#74
0#
0$
#75
1$
1%
#76
#77
#78
#79
#80
1#
0%
#81
0$
1%
#82
0#
0%
#83
1#
1%
#84
#85
0#
0%
#86
#87
1#
1%
#88
1$
0%
#89
#90
0$
1%
#91
0#
1$
#92
1#
0$
#93
1$
0%
#94
0#
1%
#95
#96
1#
0%
#97
#98
0#
0$
#99
1#
1$
#100
0#
1%
